{
    "id": "1684169302109454338",
    "screen_name": "_Project_Star_",
    "name": "Starry星曦",
    "description": "05｜社恐｜重抑｜现居昆明｜大一｜⚠️可能掉落血图警告｜",
    "profile_image_url": "https://pbs.twimg.com/profile_images/1732117668247867393/r5-4uRoW_normal.jpg",
    "profile_banner_url": "https://pbs.twimg.com/profile_banners/1684169302109454338/1705337342",
    "followers_count": 3501,
    "statuses_count": 673,
    "favourites_count": 5624,
    "listed_count": 6,
    "verified_type": null,
    "is_blue_verified": false,
    "following": true,
    "followed_by": true,
    "created_at": "2023-07-26 19:51:17 +08:00",
    "url": "https://twitter.com/_Project_Star_"
}