{
    "id": "1693683077598543877",
    "screen_name": "XLi106911724496",
    "name": "Monika",
    "description": "",
    "profile_image_url": "https://pbs.twimg.com/profile_images/1693683175053197314/tDFKW83L_normal.png",
    "profile_banner_url": null,
    "followers_count": 13,
    "statuses_count": 4,
    "favourites_count": 2,
    "listed_count": 0,
    "verified_type": null,
    "is_blue_verified": false,
    "following": false,
    "followed_by": true,
    "created_at": "2023-08-22 01:55:10 +08:00",
    "url": "https://twitter.com/XLi106911724496"
}