{
  "id": "1797857177987600384",
  "screen_name": "HCForeverBe",
  "name": "寒城FreezingCity.",
  "description": "言语无法触及之真实 我将永远与你同在",
  "profile_image_url": "https://pbs.twimg.com/profile_images/1816496757355986944/BsVVvGaA_normal.jpg",
  "profile_banner_url": "https://pbs.twimg.com/profile_banners/1797857177987600384/1717899906",
  "followers_count": 2488,
  "statuses_count": 2678,
  "favourites_count": 8267,
  "listed_count": 2,
  "verified_type": null,
  "is_blue_verified": false,
  "following": false,
  "followed_by": true,
  "created_at": "2024-06-04 13:06:07 +08:00",
  "url": "https://twitter.com/HCForeverBe"
}
