{
    "id": "727779303442747392",
    "screen_name": "0xalexs",
    "name": "alexs",
    "description": "3D printer | Resin sculptor | Muralist | Melancholy Andriods |  Lost Artist Collective",
    "profile_image_url": "https://pbs.twimg.com/profile_images/1758905535405953024/MWOnTZ2B_normal.jpg",
    "profile_banner_url": "https://pbs.twimg.com/profile_banners/727779303442747392/1708190733",
    "followers_count": 704,
    "statuses_count": 767,
    "favourites_count": 391,
    "listed_count": 1,
    "verified_type": null,
    "is_blue_verified": false,
    "following": false,
    "followed_by": true,
    "created_at": "2016-05-04 16:38:02 +08:00",
    "url": "https://twitter.com/0xalexs"
}