{
    "id": "1012920230803169280",
    "screen_name": "Quebec_MonPays",
    "name": "观测者归来，看波函数土崩瓦解，光粒子性的本征态已经到来！",
    "description": "现居魁北克/中文/English/Français\n二次元/TypeMoon/Galgame/Steam/英雄联盟/主机游戏/FNATIC\n我推：爱尔奎特，新谷灯華，荻浜茜，咲畑梨深。\nRT/Fo≠Endorsement\n尽量不支黑 随缘回FO。\n我们终将相逢在明月映照的彼方！\n月の彼方で逢いましょう！",
    "location": "IP所在国：魁北克",
    "profile_image_url": "https://pbs.twimg.com/profile_images/1897287680309829632/ra9YoYW__normal.jpg",
    "profile_banner_url": "https://pbs.twimg.com/profile_banners/1012920230803169280/1739716919",
    "followers_count": 232,
    "statuses_count": 2776,
    "favourites_count": 60848,
    "listed_count": 14,
    "verified_type": null,
    "is_blue_verified": true,
    "following": false,
    "followed_by": true,
    "created_at": "2018-06-30 12:46:16 +08:00",
    "url": "https://twitter.com/Quebec_MonPays",
    "metadata": {
        "__typename": "User",
        "id": "VXNlcjoxMDEyOTIwMjMwODAzMTY5Mjgw",
        "affiliates_highlighted_label": {},
        "has_graduated_access": true,
        "parody_commentary_fan_label": "None",
        "profile_image_shape": "Circle",
        "legacy": {
            "protected": true,
            "can_dm": true,
            "can_media_tag": false,
            "default_profile": true,
            "default_profile_image": false,
            "entities": {
                "description": {
                    "urls": []
                },
                "url": {
                    "urls": [
                        {
                            "display_url": "w1nthetarget.github.io",
                            "expanded_url": "http://w1nthetarget.github.io",
                            "url": "https://t.co/qnNGBD8W8L",
                            "indices": [
                                0,
                                23
                            ]
                        }
                    ]
                }
            },
            "fast_followers_count": 0,
            "friends_count": 6030,
            "has_custom_timelines": false,
            "is_translator": false,
            "media_count": 322,
            "pinned_tweet_ids_str": [
                "1906977803838316738"
            ],
            "possibly_sensitive": false,
            "profile_interstitial_type": "",
            "translator_type": "none",
            "url": "https://t.co/qnNGBD8W8L",
            "verified": false,
            "want_retweets": false,
            "withheld_in_countries": []
        },
        "professional": {
            "rest_id": "1574450828789907456",
            "professional_type": "Creator",
            "category": []
        },
        "tipjar_settings": {},
        "twe_private_fields": {
            "created_at": 1530333976000,
            "updated_at": 1744300366635
        }
    }
}