{
    "id": "1248637653001494529",
    "screen_name": "Fomalhautawa",
    "name": "師醬",
    "description": "你好誒，可以叫我師師。\n一些碎碎唸和日常照片。\n偶爾澀澀抽象一下啊咪。\n謝謝你呀。\n一些碎碎念指路@Ning0809pepsi",
    "location": "萱華軒",
    "profile_image_url": "https://pbs.twimg.com/profile_images/1897860278450294784/7V2pVXXB_normal.jpg",
    "profile_banner_url": "https://pbs.twimg.com/profile_banners/1248637653001494529/1741319943",
    "followers_count": 1495,
    "statuses_count": 24035,
    "favourites_count": 106896,
    "listed_count": 12,
    "verified_type": null,
    "is_blue_verified": false,
    "following": true,
    "followed_by": true,
    "created_at": "2020-04-10 23:43:19 +08:00",
    "url": "https://twitter.com/Fomalhautawa",
    "metadata": {
        "__typename": "User",
        "id": "VXNlcjoxMjQ4NjM3NjUzMDAxNDk0NTI5",
        "affiliates_highlighted_label": {},
        "has_graduated_access": true,
        "parody_commentary_fan_label": "None",
        "profile_image_shape": "Circle",
        "legacy": {
            "can_dm": true,
            "can_media_tag": false,
            "default_profile": true,
            "default_profile_image": false,
            "entities": {
                "description": {
                    "urls": []
                },
                "url": {
                    "urls": [
                        {
                            "display_url": "ngl.link/shisw1",
                            "expanded_url": "https://ngl.link/shisw1",
                            "url": "https://t.co/UqBs9GEVAT",
                            "indices": [
                                0,
                                23
                            ]
                        }
                    ]
                }
            },
            "fast_followers_count": 0,
            "friends_count": 262,
            "has_custom_timelines": false,
            "is_translator": false,
            "media_count": 40,
            "pinned_tweet_ids_str": [
                "1900761409329524973"
            ],
            "possibly_sensitive": false,
            "profile_interstitial_type": "",
            "translator_type": "none",
            "url": "https://t.co/UqBs9GEVAT",
            "verified": false,
            "want_retweets": true,
            "withheld_in_countries": []
        },
        "tipjar_settings": {
            "is_enabled": false
        },
        "twe_private_fields": {
            "created_at": 1586533399000,
            "updated_at": 1742120128126
        }
    }
}