{
    "id": "1651062764134096897",
    "screen_name": "weiraolewoba",
    "name": "喂饶了我吧",
    "description": "你好！！我是小喂 我不喜欢MBTI 我不是黄推 我不是地雷女 关注我没有涩图和血图看 记得善用屏蔽祝你天天开心 这里是我的垃圾桶互转不用啦 永远的RIP睡裤",
    "location": "111大哥真的吗",
    "profile_image_url": "https://pbs.twimg.com/profile_images/1850787856668884992/_pBjBnio_normal.jpg",
    "profile_banner_url": "https://pbs.twimg.com/profile_banners/1651062764134096897/1736234266",
    "followers_count": 1310,
    "statuses_count": 1130,
    "favourites_count": 1784,
    "listed_count": 1,
    "verified_type": null,
    "is_blue_verified": false,
    "following": true,
    "followed_by": true,
    "created_at": "2023-04-26 11:17:49 +08:00",
    "url": "https://twitter.com/weiraolewoba",
    "metadata": {
        "__typename": "User",
        "id": "VXNlcjoxNjUxMDYyNzY0MTM0MDk2ODk3",
        "affiliates_highlighted_label": {},
        "has_graduated_access": true,
        "parody_commentary_fan_label": "None",
        "profile_image_shape": "Circle",
        "legacy": {
            "can_dm": true,
            "can_media_tag": true,
            "default_profile": true,
            "default_profile_image": false,
            "entities": {
                "description": {
                    "urls": []
                }
            },
            "fast_followers_count": 0,
            "friends_count": 1246,
            "has_custom_timelines": false,
            "is_translator": false,
            "media_count": 56,
            "pinned_tweet_ids_str": [
                "1885934532479860976"
            ],
            "possibly_sensitive": false,
            "profile_interstitial_type": "",
            "translator_type": "none",
            "verified": false,
            "want_retweets": true,
            "withheld_in_countries": []
        },
        "tipjar_settings": {
            "is_enabled": false
        },
        "twe_private_fields": {
            "created_at": 1682479069000,
            "updated_at": 1740914900796
        }
    }
}