{
    "id": "1765072369599795202",
    "screen_name": "Kaoruko157",
    "name": "小混沌",
    "description": "私たくさんの人に助けられてま す、この気持ちをいつか返せる人",
    "profile_image_url": "https://pbs.twimg.com/profile_images/1792135388347457536/iBr2rRJL_normal.jpg",
    "profile_banner_url": "https://pbs.twimg.com/profile_banners/1765072369599795202/1732871023",
    "followers_count": 418,
    "statuses_count": 413,
    "favourites_count": 564,
    "listed_count": 0,
    "verified_type": null,
    "is_blue_verified": false,
    "following": true,
    "followed_by": true,
    "created_at": "2024-03-06 01:50:37 +08:00",
    "url": "https://twitter.com/Kaoruko157",
    "metadata": {
        "__typename": "User",
        "id": "VXNlcjoxNzY1MDcyMzY5NTk5Nzk1MjAy",
        "affiliates_highlighted_label": {},
        "has_graduated_access": true,
        "parody_commentary_fan_label": "None",
        "profile_image_shape": "Circle",
        "legacy": {
            "protected": true,
            "can_dm": true,
            "can_media_tag": false,
            "default_profile": true,
            "default_profile_image": false,
            "entities": {
                "description": {
                    "urls": []
                }
            },
            "fast_followers_count": 0,
            "friends_count": 590,
            "has_custom_timelines": false,
            "is_translator": false,
            "location": "",
            "media_count": 29,
            "pinned_tweet_ids_str": [
                "1887366866001404262"
            ],
            "possibly_sensitive": false,
            "profile_interstitial_type": "",
            "translator_type": "none",
            "verified": false,
            "want_retweets": true,
            "withheld_in_countries": []
        },
        "tipjar_settings": {},
        "twe_private_fields": {
            "created_at": 1709661037000,
            "updated_at": 1739589260496
        }
    }
}