{
  "id": "1818337984191905794",
  "screen_name": "ultra_mitsuki4",
  "name": "mtsuki4.0",
  "description": "我又重生了*4，这里依旧是小米，依旧重抑重焦，依旧很穷，依旧查成分互fo",
  "profile_image_url": "https://pbs.twimg.com/profile_images/1818338518848225284/vHKgS1xL_normal.jpg",
  "profile_banner_url": "https://pbs.twimg.com/profile_banners/1818337984191905794/1722360678",
  "followers_count": 264,
  "statuses_count": 392,
  "favourites_count": 204,
  "listed_count": 0,
  "verified_type": null,
  "is_blue_verified": false,
  "following": true,
  "followed_by": true,
  "created_at": "2024-07-31 01:29:04 +08:00",
  "url": "https://twitter.com/ultra_mitsuki4"
}
