{
    "id": "1844025283676094464",
    "screen_name": "Konekoutena",
    "name": "枫糖小猫",
    "description": "一个在NPD原生家庭受伤的孩子，愿用知识治愈每一颗受伤的心…油管号“夜昕时光”，关注我的频道，了解更多的知识 https://t.co/VWQrtRQrcm",
    "location": "Aoba-ku, Miyagi",
    "profile_image_url": "https://pbs.twimg.com/profile_images/1894011794416357376/sd-Gqb3F_normal.jpg",
    "profile_banner_url": "https://pbs.twimg.com/profile_banners/1844025283676094464/1740804109",
    "followers_count": 7118,
    "statuses_count": 9913,
    "favourites_count": 4415,
    "listed_count": 27,
    "verified_type": null,
    "is_blue_verified": true,
    "following": true,
    "followed_by": true,
    "created_at": "2024-10-09 22:41:12 +08:00",
    "url": "https://twitter.com/Konekoutena",
    "metadata": {
        "__typename": "User",
        "id": "VXNlcjoxODQ0MDI1MjgzNjc2MDk0NDY0",
        "affiliates_highlighted_label": {},
        "has_graduated_access": true,
        "parody_commentary_fan_label": "None",
        "profile_image_shape": "Circle",
        "legacy": {
            "can_dm": true,
            "can_media_tag": false,
            "default_profile": true,
            "default_profile_image": false,
            "entities": {
                "description": {
                    "urls": [
                        {
                            "display_url": "youtube.com/@yexintime",
                            "expanded_url": "https://youtube.com/@yexintime",
                            "url": "https://t.co/VWQrtRQrcm",
                            "indices": [
                                55,
                                78
                            ]
                        }
                    ]
                },
                "url": {
                    "urls": [
                        {
                            "display_url": "youtube.com/@yexintime",
                            "expanded_url": "https://youtube.com/@yexintime",
                            "url": "https://t.co/VWQrtRQrcm",
                            "indices": [
                                0,
                                23
                            ]
                        }
                    ]
                }
            },
            "fast_followers_count": 0,
            "friends_count": 1377,
            "has_custom_timelines": false,
            "is_translator": false,
            "media_count": 3368,
            "pinned_tweet_ids_str": [
                "1895473306524057902"
            ],
            "possibly_sensitive": false,
            "profile_interstitial_type": "",
            "translator_type": "none",
            "url": "https://t.co/VWQrtRQrcm",
            "verified": false,
            "want_retweets": true,
            "withheld_in_countries": []
        },
        "tipjar_settings": {
            "is_enabled": true
        },
        "twe_private_fields": {
            "created_at": 1728484872000,
            "updated_at": 1740914905097
        }
    }
}