{
    "id": "1882056461599326208",
    "screen_name": "yqua_",
    "name": "聒噪的铨酱",
    "description": "文静的铨酱@59ryq 这里是小铨的荒诞故事录 「故事要从这里开始讲起」",
    "location": "",
    "profile_image_url": "https://pbs.twimg.com/profile_images/1882056816328339456/r_Ao-ECg_normal.jpg",
    "profile_banner_url": "https://pbs.twimg.com/profile_banners/1882056461599326208/1738758203",
    "followers_count": 18,
    "statuses_count": 3,
    "favourites_count": 19,
    "listed_count": 0,
    "verified_type": null,
    "is_blue_verified": false,
    "following": true,
    "followed_by": true,
    "created_at": "2025-01-22 21:23:46 +08:00",
    "url": "https://twitter.com/yqua_",
    "metadata": {
        "__typename": "User",
        "id": "VXNlcjoxODgyMDU2NDYxNTk5MzI2MjA4",
        "affiliates_highlighted_label": {},
        "has_graduated_access": true,
        "parody_commentary_fan_label": "None",
        "profile_image_shape": "Circle",
        "legacy": {
            "protected": true,
            "can_dm": true,
            "can_media_tag": false,
            "default_profile": true,
            "default_profile_image": false,
            "entities": {
                "description": {
                    "urls": []
                }
            },
            "fast_followers_count": 0,
            "friends_count": 18,
            "has_custom_timelines": false,
            "is_translator": false,
            "media_count": 0,
            "pinned_tweet_ids_str": [],
            "possibly_sensitive": false,
            "profile_interstitial_type": "",
            "translator_type": "none",
            "verified": false,
            "want_retweets": true,
            "withheld_in_countries": []
        },
        "tipjar_settings": {},
        "twe_private_fields": {
            "created_at": 1737552226000,
            "updated_at": 1740914900796
        }
    }
}