{
    "id": "896324794773233664",
    "screen_name": "LindaQee2000",
    "name": "Linda Qee",
    "description": "一只被天帝开了玩笑的mtf，大学在校。信条：我要扼住命运的咽喉！！！",
    "location": "成华大道二仙桥西",
    "profile_image_url": "https://pbs.twimg.com/profile_images/1262702647087214592/xH65KzJj_normal.jpg",
    "profile_banner_url": null,
    "followers_count": 199,
    "statuses_count": 36,
    "favourites_count": 210,
    "listed_count": 0,
    "verified_type": null,
    "is_blue_verified": false,
    "following": false,
    "followed_by": true,
    "created_at": "2017-08-12 18:57:38 +08:00",
    "url": "https://twitter.com/LindaQee2000",
    "metadata": {
        "__typename": "User",
        "id": "VXNlcjo4OTYzMjQ3OTQ3NzMyMzM2NjQ=",
        "affiliates_highlighted_label": {},
        "has_graduated_access": true,
        "parody_commentary_fan_label": "None",
        "profile_image_shape": "Circle",
        "legacy": {
            "can_dm": true,
            "can_media_tag": true,
            "default_profile": true,
            "default_profile_image": false,
            "entities": {
                "description": {
                    "urls": []
                }
            },
            "fast_followers_count": 0,
            "friends_count": 182,
            "has_custom_timelines": false,
            "is_translator": false,
            "media_count": 5,
            "pinned_tweet_ids_str": [
                "1242125972767301632"
            ],
            "possibly_sensitive": false,
            "profile_interstitial_type": "",
            "translator_type": "none",
            "verified": false,
            "want_retweets": false,
            "withheld_in_countries": []
        },
        "tipjar_settings": {},
        "twe_private_fields": {
            "created_at": 1502535458000,
            "updated_at": 1744344981624
        }
    }
}