{
    "id": "1372184630753853444",
    "screen_name": "2temisinin",
    "name": "氯鸮西泮",
    "description": "最爱@haku_dabai｜鸮｜呼号BH6RQG",
    "profile_image_url": "https://pbs.twimg.com/profile_images/1894978786338222080/ksYWNZSK_normal.jpg",
    "profile_banner_url": "https://pbs.twimg.com/profile_banners/1372184630753853444/1679410047",
    "followers_count": 2788,
    "friends_count": 1615,
    "statuses_count": 2970,
    "favourites_count": 32228,
    "listed_count": 3,
    "location": "罗德岛",
    "website": null,
    "birthdate": null,
    "verified_type": null,
    "is_blue_verified": false,
    "following": true,
    "followed_by": true,
    "can_dm": true,
    "protected": false,
    "created_at": "2000-01-01 00:00:00 +08:00",
    "url": "https://twitter.com/2temisinin",
    "metadata": {
        "__typename": "User",
        "id": "VXNlcjoxMzcyMTg0NjMwNzUzODUzNDQ0",
        "affiliates_highlighted_label": {},
        "avatar": {
            "image_url": "https://pbs.twimg.com/profile_images/1894978786338222080/ksYWNZSK_normal.jpg"
        },
        "core": {
            "created_at": "Wed Mar 17 13:54:56 +0000 2021",
            "name": "氯鸮西泮",
            "screen_name": "2temisinin"
        },
        "dm_permissions": {
            "can_dm": true
        },
        "has_graduated_access": true,
        "legacy": {
            "default_profile": true,
            "default_profile_image": false,
            "entities": {
                "description": {
                    "urls": []
                }
            },
            "fast_followers_count": 0,
            "friends_count": 1615,
            "has_custom_timelines": false,
            "is_translator": false,
            "media_count": 307,
            "pinned_tweet_ids_str": [
                "1894930997873127616"
            ],
            "possibly_sensitive": false,
            "profile_interstitial_type": "",
            "translator_type": "none",
            "want_retweets": true,
            "withheld_in_countries": []
        },
        "location": {
            "location": "罗德岛"
        },
        "media_permissions": {
            "can_media_tag": true
        },
        "parody_commentary_fan_label": "None",
        "profile_image_shape": "Circle",
        "privacy": {
            "protected": false
        },
        "relationship_perspectives": {
            "followed_by": true,
            "following": true
        },
        "tipjar_settings": {},
        "verification": {
            "verified": false
        },
        "twe_private_fields": {
            "created_at": 946656000000,
            "updated_at": 1749219066708
        }
    }
}