{
    "id": "1449417312520392705",
    "screen_name": "123nhh_awa",
    "name": "星回",
    "description": "原名123nhh，回fo私信，精神状态差，目前应该不会去死，可以长时间赛博看乐子",
    "location": "",
    "profile_image_url": "https://pbs.twimg.com/profile_images/1822094492738236416/8waaV6Cg_normal.jpg",
    "profile_banner_url": null,
    "followers_count": 1333,
    "friends_count": 1139,
    "statuses_count": 141,
    "favourites_count": 3884,
    "listed_count": 2,
    "website": null,
    "birthdate": null,
    "verified_type": null,
    "is_blue_verified": false,
    "following": true,
    "followed_by": true,
    "can_dm": true,
    "protected": null,
    "created_at": "2021-10-17 00:50:02 +08:00",
    "url": "https://twitter.com/123nhh_awa",
    "metadata": {
        "__typename": "User",
        "id": "VXNlcjoxNDQ5NDE3MzEyNTIwMzkyNzA1",
        "affiliates_highlighted_label": {},
        "has_graduated_access": true,
        "legacy": {
            "can_dm": true,
            "can_media_tag": true,
            "default_profile": true,
            "default_profile_image": false,
            "entities": {
                "description": {
                    "urls": []
                }
            },
            "fast_followers_count": 0,
            "friends_count": 1139,
            "has_custom_timelines": false,
            "is_translator": false,
            "media_count": 17,
            "pinned_tweet_ids_str": [
                "1870520569227272445"
            ],
            "possibly_sensitive": false,
            "profile_interstitial_type": "",
            "translator_type": "none",
            "verified": false,
            "want_retweets": true,
            "withheld_in_countries": []
        },
        "parody_commentary_fan_label": "None",
        "profile_image_shape": "Circle",
        "professional": {
            "rest_id": "1614641883002859520",
            "professional_type": "Creator",
            "category": []
        },
        "tipjar_settings": {
            "is_enabled": false
        },
        "twe_private_fields": {
            "created_at": 1634403002000,
            "updated_at": 1746277400306
        }
    }
}