{
    "id": "1672822866986024961",
    "screen_name": "Lycaropia",
    "name": "居眠姬",
    "description": "Aspie | TS Fullstack | Transgirl 🏳️‍⚧️ | Les | GF @CatTalkerMitaka\nLOVE ❤ FOREVER",
    "location": "384,400km",
    "profile_image_url": "https://pbs.twimg.com/profile_images/1905253739625320448/sKopIlPH_normal.jpg",
    "profile_banner_url": "https://pbs.twimg.com/profile_banners/1672822866986024961/1687668245",
    "followers_count": 1292,
    "statuses_count": 9101,
    "favourites_count": 71478,
    "listed_count": 1,
    "verified_type": null,
    "is_blue_verified": false,
    "following": true,
    "followed_by": true,
    "created_at": "2023-06-25 12:24:03 +08:00",
    "url": "https://twitter.com/Lycaropia",
    "metadata": {
        "__typename": "User",
        "id": "VXNlcjoxNjcyODIyODY2OTg2MDI0OTYx",
        "affiliates_highlighted_label": {},
        "has_graduated_access": true,
        "parody_commentary_fan_label": "None",
        "profile_image_shape": "Circle",
        "legacy": {
            "can_dm": true,
            "can_media_tag": false,
            "default_profile": true,
            "default_profile_image": false,
            "entities": {
                "description": {
                    "urls": []
                }
            },
            "fast_followers_count": 0,
            "friends_count": 1033,
            "has_custom_timelines": false,
            "is_translator": false,
            "media_count": 212,
            "pinned_tweet_ids_str": [
                "1835227356170190958"
            ],
            "possibly_sensitive": false,
            "profile_interstitial_type": "",
            "translator_type": "none",
            "verified": false,
            "want_retweets": true,
            "withheld_in_countries": []
        },
        "tipjar_settings": {},
        "twe_private_fields": {
            "created_at": 1687667043000,
            "updated_at": 1744350099731
        }
    }
}