{
    "id": "1695452816658325504",
    "name": "珞雪 （小号.jpg",
    "screen_name": "luoxuealt",
    "description": "只是个不用的账号而已～～",
    "location": "长沙",
    "url": null,
    "entities": {
        "description": {
            "urls": []
        }
    },
    "protected": false,
    "followers_count": 900,
    "friends_count": 740,
    "listed_count": 1,
    "created_at": "Sat Aug 26 15:07:16 +0000 2023",
    "favourites_count": 3577,
    "verified": false,
    "statuses_count": 1951,
    "media_count": 230,
    "profile_background_image_url": null,
    "profile_background_tile": false,
    "profile_image_url": "http://pbs.twimg.com/profile_images/1697598311883304960/jDWBHRM7_normal.jpg",
    "profile_banner_url": "https://pbs.twimg.com/profile_banners/1695452816658325504/1730814181",
    "profile_use_background_image": true,
    "has_extended_profile": true,
    "default_profile": true,
    "default_profile_image": false,
    "pinned_tweet_ids": [
        1948362205847855579
    ],
    "pinned_tweet_ids_str": [
        "1948362205847855579"
    ],
    "has_custom_timelines": false,
    "can_dm": null,
    "can_media_tag": true,
    "following": true,
    "follow_request_sent": false,
    "notifications": false,
    "muting": false,
    "advertiser_account_type": "none",
    "advertiser_account_service_levels": [],
    "business_profile_state": "none",
    "translator_type": "none",
    "withheld_in_countries": [],
    "followed_by": true,
    "ext_is_blue_verified": false,
    "require_some_consent": false
}