{
    "id": "1771725999501373440",
    "screen_name": "fhsknxkxoaejt",
    "name": "maku224",
    "description": "我好焦慮 我焦慮成績焦慮未來焦慮才能焦慮身材焦慮容貌焦慮朋友\n喵",
    "profile_image_url": "https://pbs.twimg.com/profile_images/1823888471309832192/BNqb3W26_normal.jpg",
    "profile_banner_url": "https://pbs.twimg.com/profile_banners/1771725999501373440/1723683977",
    "followers_count": 33,
    "friends_count": 49,
    "statuses_count": 1198,
    "favourites_count": 5361,
    "listed_count": 0,
    "location": "24小時位於家中",
    "website": null,
    "birthdate": null,
    "verified_type": null,
    "is_blue_verified": false,
    "following": false,
    "followed_by": true,
    "can_dm": true,
    "protected": false,
    "created_at": "2024-03-24 10:30:08 +08:00",
    "url": "https://twitter.com/fhsknxkxoaejt",
    "metadata": {
        "__typename": "User",
        "id": "VXNlcjoxNzcxNzI1OTk5NTAxMzczNDQw",
        "affiliates_highlighted_label": {},
        "avatar": {
            "image_url": "https://pbs.twimg.com/profile_images/1823888471309832192/BNqb3W26_normal.jpg"
        },
        "core": {
            "created_at": "Sun Mar 24 02:30:08 +0000 2024",
            "name": "maku224",
            "screen_name": "fhsknxkxoaejt"
        },
        "dm_permissions": {
            "can_dm": true
        },
        "has_graduated_access": true,
        "legacy": {
            "default_profile": true,
            "default_profile_image": false,
            "entities": {
                "description": {
                    "urls": []
                }
            },
            "fast_followers_count": 0,
            "friends_count": 49,
            "has_custom_timelines": false,
            "is_translator": false,
            "media_count": 81,
            "pinned_tweet_ids_str": [
                "1872206826743447792"
            ],
            "possibly_sensitive": false,
            "profile_interstitial_type": "",
            "translator_type": "none",
            "want_retweets": false,
            "withheld_in_countries": []
        },
        "location": {
            "location": "24小時位於家中"
        },
        "media_permissions": {
            "can_media_tag": false
        },
        "parody_commentary_fan_label": "None",
        "profile_image_shape": "Circle",
        "privacy": {
            "protected": false
        },
        "relationship_perspectives": {
            "followed_by": true,
            "following": false
        },
        "tipjar_settings": {},
        "verification": {
            "verified": false
        },
        "twe_private_fields": {
            "created_at": 1711247408000,
            "updated_at": 1752846535035
        }
    }
}