{
    "id": "1845491203124441093",
    "screen_name": "yu_huacs",
    "name": "余華成霜",
    "description": "余华 单车佬 宅 双 抽象 我的世界 Allez sprint tfsa jhf06 \nOCR5500 Lain od 双相 精神max 公路车 二次元 09 原产于shanghai 叠加状态 \n第二人格 @yuhuacs5570",
    "profile_image_url": "https://pbs.twimg.com/profile_images/1922978167616143360/O6HKnIve_normal.jpg",
    "profile_banner_url": "https://pbs.twimg.com/profile_banners/1845491203124441093/1740625782",
    "followers_count": 894,
    "friends_count": 974,
    "statuses_count": 12572,
    "favourites_count": 73582,
    "listed_count": 10,
    "location": "shanghai",
    "website": "https://t.co/fGARwmdoNl",
    "birthdate": null,
    "verified_type": null,
    "is_blue_verified": false,
    "following": true,
    "followed_by": true,
    "can_dm": true,
    "protected": false,
    "created_at": "2024-10-13 23:46:25 +08:00",
    "url": "https://twitter.com/yu_huacs",
    "metadata": {
        "__typename": "User",
        "id": "VXNlcjoxODQ1NDkxMjAzMTI0NDQxMDkz",
        "affiliates_highlighted_label": {},
        "avatar": {
            "image_url": "https://pbs.twimg.com/profile_images/1922978167616143360/O6HKnIve_normal.jpg"
        },
        "core": {
            "created_at": "Sun Oct 13 15:46:25 +0000 2024",
            "name": "余華成霜",
            "screen_name": "yu_huacs"
        },
        "dm_permissions": {
            "can_dm": true
        },
        "has_graduated_access": true,
        "legacy": {
            "default_profile": true,
            "default_profile_image": false,
            "entities": {
                "description": {
                    "urls": []
                },
                "url": {
                    "urls": [
                        {
                            "display_url": "ngl.link/yu_huacs",
                            "expanded_url": "https://ngl.link/yu_huacs",
                            "url": "https://t.co/fGARwmdoNl",
                            "indices": [
                                0,
                                23
                            ]
                        }
                    ]
                }
            },
            "fast_followers_count": 0,
            "friends_count": 974,
            "has_custom_timelines": false,
            "is_translator": false,
            "media_count": 1500,
            "pinned_tweet_ids_str": [],
            "possibly_sensitive": false,
            "profile_interstitial_type": "",
            "translator_type": "none",
            "url": "https://t.co/fGARwmdoNl",
            "want_retweets": true,
            "withheld_in_countries": []
        },
        "location": {
            "location": "shanghai"
        },
        "media_permissions": {
            "can_media_tag": true
        },
        "parody_commentary_fan_label": "None",
        "profile_image_shape": "Circle",
        "privacy": {
            "protected": false
        },
        "relationship_perspectives": {
            "followed_by": true,
            "following": true
        },
        "tipjar_settings": {
            "is_enabled": true
        },
        "verification": {
            "verified": false
        },
        "twe_private_fields": {
            "created_at": 1728834385000,
            "updated_at": 1750232257458
        }
    }
}