{
    "id": "1908821896021581824",
    "screen_name": "soyorin_love123",
    "name": "长崎素世",
    "description": "也许是某wet",
    "profile_image_url": "https://pbs.twimg.com/profile_images/1908822174544326656/nXtCpJpb_normal.jpg",
    "profile_banner_url": "https://pbs.twimg.com/profile_banners/1908821896021581824/1743933654",
    "followers_count": 250,
    "friends_count": 377,
    "statuses_count": 482,
    "favourites_count": 5825,
    "listed_count": 0,
    "location": "",
    "website": null,
    "birthdate": null,
    "verified_type": null,
    "is_blue_verified": false,
    "following": false,
    "followed_by": true,
    "can_dm": true,
    "protected": false,
    "created_at": "2025-04-06 17:59:50 +08:00",
    "url": "https://twitter.com/soyorin_love123",
    "metadata": {
        "__typename": "User",
        "id": "VXNlcjoxOTA4ODIxODk2MDIxNTgxODI0",
        "affiliates_highlighted_label": {},
        "avatar": {
            "image_url": "https://pbs.twimg.com/profile_images/1908822174544326656/nXtCpJpb_normal.jpg"
        },
        "core": {
            "created_at": "Sun Apr 06 09:59:50 +0000 2025",
            "name": "长崎素世",
            "screen_name": "soyorin_love123"
        },
        "dm_permissions": {
            "can_dm": true
        },
        "has_graduated_access": true,
        "legacy": {
            "default_profile": true,
            "default_profile_image": false,
            "entities": {
                "description": {
                    "urls": []
                }
            },
            "fast_followers_count": 0,
            "friends_count": 377,
            "has_custom_timelines": false,
            "is_translator": false,
            "media_count": 32,
            "pinned_tweet_ids_str": [
                "1942512724031987992"
            ],
            "possibly_sensitive": false,
            "profile_interstitial_type": "",
            "translator_type": "none",
            "want_retweets": false,
            "withheld_in_countries": []
        },
        "location": {
            "location": ""
        },
        "media_permissions": {
            "can_media_tag": false
        },
        "parody_commentary_fan_label": "None",
        "profile_image_shape": "Circle",
        "privacy": {
            "protected": false
        },
        "relationship_perspectives": {
            "followed_by": true,
            "following": false
        },
        "tipjar_settings": {},
        "verification": {
            "verified": false
        },
        "twe_private_fields": {
            "created_at": 1743933590000,
            "updated_at": 1752846528414
        }
    }
}