{
    "id": "3186322153",
    "screen_name": "aa123429181tw",
    "name": "Astray",
    "description": "嗨!我叫做ASTRAY~\n興趣是騎車,塗鴉,組模型和打生存遊戲.... (・ω・)\n其實我會的也不多啦~\n\n還有我是男的,只是喜歡穿女裝而已,而且沒有很漂亮...\n還會放奇怪的照片,我都會設置敏感注意,介意的請別點開 (つд⊂)\n\n話題都OK~\n另外,我的畫技很差所以不接任何委託喔~ (´・ω・`)",
    "profile_image_url": "https://pbs.twimg.com/profile_images/1876658964844449792/dQuuXver_normal.jpg",
    "profile_banner_url": "https://pbs.twimg.com/profile_banners/3186322153/1669708448",
    "followers_count": 708,
    "friends_count": 1559,
    "statuses_count": 63530,
    "favourites_count": 150167,
    "listed_count": 16,
    "location": "台灣",
    "website": "https://t.co/EYNZRnOMbn",
    "birthdate": null,
    "verified_type": null,
    "is_blue_verified": false,
    "following": true,
    "followed_by": true,
    "can_dm": true,
    "protected": false,
    "created_at": "2000-01-01 00:00:00 +08:00",
    "url": "https://twitter.com/aa123429181tw",
    "metadata": {
        "__typename": "User",
        "id": "VXNlcjozMTg2MzIyMTUz",
        "affiliates_highlighted_label": {},
        "avatar": {
            "image_url": "https://pbs.twimg.com/profile_images/1876658964844449792/dQuuXver_normal.jpg"
        },
        "core": {
            "created_at": "Tue May 05 14:26:08 +0000 2015",
            "name": "Astray",
            "screen_name": "aa123429181tw"
        },
        "dm_permissions": {
            "can_dm": true
        },
        "has_graduated_access": true,
        "legacy": {
            "default_profile": true,
            "default_profile_image": false,
            "entities": {
                "description": {
                    "urls": []
                },
                "url": {
                    "urls": [
                        {
                            "display_url": "pixiv.net/users/960150",
                            "expanded_url": "http://pixiv.net/users/960150",
                            "url": "https://t.co/EYNZRnOMbn",
                            "indices": [
                                0,
                                23
                            ]
                        }
                    ]
                }
            },
            "fast_followers_count": 0,
            "friends_count": 1559,
            "has_custom_timelines": false,
            "is_translator": false,
            "media_count": 2512,
            "pinned_tweet_ids_str": [
                "1677615650255306752"
            ],
            "possibly_sensitive": false,
            "profile_interstitial_type": "",
            "translator_type": "none",
            "url": "https://t.co/EYNZRnOMbn",
            "want_retweets": true,
            "withheld_in_countries": []
        },
        "location": {
            "location": "台灣"
        },
        "media_permissions": {
            "can_media_tag": true
        },
        "parody_commentary_fan_label": "None",
        "profile_image_shape": "Circle",
        "privacy": {
            "protected": false
        },
        "relationship_perspectives": {
            "followed_by": true,
            "following": true
        },
        "tipjar_settings": {},
        "verification": {
            "verified": false
        },
        "twe_private_fields": {
            "created_at": 946656000000,
            "updated_at": 1749219057411
        }
    }
}