{
    "id": "727779303442747392",
    "screen_name": "moonshot_alxs",
    "name": "Moonshot Official Support",
    "description": "Buy & Sell Memes with Apple Pay. Live on App Store and Google Play in 130+ Countries | Get support: https://t.co/VaAHajMcOJ",
    "profile_image_url": "https://pbs.twimg.com/profile_images/1884337475826462720/wvfWJCum_normal.jpg",
    "profile_banner_url": "https://pbs.twimg.com/profile_banners/727779303442747392/1738096050",
    "followers_count": 708,
    "statuses_count": 1014,
    "favourites_count": 0,
    "listed_count": 1,
    "verified_type": null,
    "is_blue_verified": false,
    "following": false,
    "followed_by": true,
    "created_at": "2016-05-04 16:38:02 +08:00",
    "url": "https://twitter.com/moonshot_alxs"
}